pyfreenas/__init__.py
pyfreenas/disk.py
pyfreenas/virtualmachine.py
pyfreenas/websockets_custom.py
pyfreenas-0.1.0.dist-info/LICENSE
pyfreenas-0.1.0.dist-info/METADATA
pyfreenas-0.1.0.dist-info/WHEEL
pyfreenas-0.1.0.dist-info/top_level.txt
pyfreenas-0.1.0.dist-info/RECORD
