Metadata-Version: 2.1
Name: pyfreenas
Version: 0.1.0
Summary: A Python module for the FreeNAS websocket API.
Home-page: https://github.com/sdwilsh/py-freenas
Author: Shawn Wilsher
Author-email: me@shawnwilsher.com
License: UNKNOWN
Download-URL: https://github.com/sdwilsh/py-freenas/archive/0.1.0.tar.gz
Project-URL: Bug Reports, https://github.com/sdwilsh/py-freenas/issues
Platform: UNKNOWN
Classifier: Development Status :: 3 - Alpha
Classifier: License :: OSI Approved :: MIT License
Classifier: Operating System :: OS Independent
Classifier: Programming Language :: Python :: 3.8
Requires-Python: >3.8, <4
Requires-Dist: websockets (==8.1)
Requires-Dist: meteor-ejson (==1.1.0)
